uminifier/__init__.py
uminifier-0.1.0.dist-info/METADATA
uminifier-0.1.0.dist-info/WHEEL
uminifier-0.1.0.dist-info/entry_points.txt
uminifier-0.1.0.dist-info/top_level.txt
uminifier-0.1.0.dist-info/RECORD
