Metadata-Version: 2.1
Name: uminifier
Version: 0.1.0
Summary: A small example package
Home-page: https://github.com/yeyeto2788/uminifier
Author: Juan Biondi
Author-email: juanernestobiondi@gmail.com
License: UNKNOWN
Platform: UNKNOWN
Classifier: Programming Language :: Python :: 3
Classifier: License :: OSI Approved :: MIT License
Classifier: Operating System :: OS Independent
Requires-Python: >=3.6
Requires-Dist: pyminifier (>=2.1)
Requires-Dist: mpy-cross (>=1.12)
